llama_index/__init__.py
llama_index/graph_stores/__init__.py
llama_index/graph_stores/arcadedb/__init__.py
llama_index/graph_stores/arcadedb/arcadedb_property_graph.py
llama_index/graph_stores/arcadedb/base.py
llama_index_graph_stores_arcadedb-0.3.0.dist-info/METADATA
llama_index_graph_stores_arcadedb-0.3.0.dist-info/WHEEL
llama_index_graph_stores_arcadedb-0.3.0.dist-info/licenses/LICENSE
llama_index_graph_stores_arcadedb-0.3.0.dist-info/RECORD
