Metadata-Version: 2.4
Name: llama-index-graph-stores-arcadedb
Version: 0.3.0
Summary: LlamaIndex Graph Stores integration for ArcadeDB - Multi-Model Database with Graph, Document, Key-Value, Vector, and Time-Series support
Project-URL: Homepage, https://github.com/stevereiner/arcadedb-llama-index
Project-URL: Documentation, https://docs.llamaindex.ai/en/stable/module_guides/storing/graph_stores/
Project-URL: Repository, https://github.com/stevereiner/arcadedb-llama-index
Project-URL: Bug Tracker, https://github.com/stevereiner/arcadedb-llama-index/issues
Project-URL: ArcadeDB Documentation, https://docs.arcadedb.com/
Project-URL: ArcadeDB Homepage, https://arcadedb.com/
Author: Adams Rosales, ExtReMLapin, Steve Reiner
Maintainer: Steve Reiner
License-Expression: Apache-2.0
License-File: LICENSE
Keywords: arcadedb,database,graph-store,graphrag,knowledge-graph,llama-index,multi-model,property-graph,rag,vector-search
Classifier: Development Status :: 4 - Beta
Classifier: Intended Audience :: Developers
Classifier: License :: OSI Approved :: Apache Software License
Classifier: Operating System :: OS Independent
Classifier: Programming Language :: Python :: 3
Classifier: Programming Language :: Python :: 3.10
Classifier: Programming Language :: Python :: 3.11
Classifier: Programming Language :: Python :: 3.12
Classifier: Programming Language :: Python :: 3.13
Classifier: Topic :: Database
Classifier: Topic :: Database :: Database Engines/Servers
Classifier: Topic :: Scientific/Engineering :: Artificial Intelligence
Classifier: Topic :: Software Development :: Libraries :: Python Modules
Classifier: Topic :: Text Processing :: Indexing
Classifier: Typing :: Typed
Requires-Python: <4.0,>=3.10
Requires-Dist: arcadedb-python>=0.3.0
Requires-Dist: llama-index-core<0.15,>=0.13.0
Provides-Extra: dev
Requires-Dist: black>=23.0.0; extra == 'dev'
Requires-Dist: docker>=6.0.0; extra == 'dev'
Requires-Dist: isort>=5.12.0; extra == 'dev'
Requires-Dist: mypy>=1.0.0; extra == 'dev'
Requires-Dist: pytest-cov>=4.0.0; extra == 'dev'
Requires-Dist: pytest-mock>=3.10.0; extra == 'dev'
Requires-Dist: pytest>=7.0.0; extra == 'dev'
Requires-Dist: ruff>=0.1.0; extra == 'dev'
